goodow/workflow/github/send_alert.py
goodow/workflow/observability/logger.py
goodow/workflow/observability/util.py
goodow_workflow-0.5.1.dist-info/METADATA
goodow_workflow-0.5.1.dist-info/WHEEL
goodow_workflow-0.5.1.dist-info/entry_points.txt
goodow_workflow-0.5.1.dist-info/RECORD
