Metadata-Version: 2.1
Name: goodow-workflow
Version: 0.5.1
Summary: A small example package
Home-page: https://github.com/larrytin/goodow-workflow
License: MIT
Author: Larry Tin
Author-email: dev@goodow.com
Requires-Python: >=3.9
Classifier: License :: OSI Approved :: MIT License
Classifier: Programming Language :: Python :: 3
Classifier: Programming Language :: Python :: 3.9
Classifier: Programming Language :: Python :: 3.10
Classifier: Programming Language :: Python :: 3.11
Classifier: Programming Language :: Python :: 3.12
Provides-Extra: telegram
Requires-Dist: python-telegram-bot[rate-limiter] (>=21) ; extra == "telegram"
Project-URL: Repository, https://github.com/larrytin/goodow-workflow
